llama_index/embeddings/voyageai/__init__.py
llama_index/embeddings/voyageai/base.py
llama_index_embeddings_voyageai-0.5.3.dist-info/METADATA
llama_index_embeddings_voyageai-0.5.3.dist-info/WHEEL
llama_index_embeddings_voyageai-0.5.3.dist-info/licenses/LICENSE
llama_index_embeddings_voyageai-0.5.3.dist-info/RECORD
