Metadata-Version: 2.4
Name: llama-index-embeddings-voyageai
Version: 0.5.3
Summary: llama-index embeddings voyageai integration
Author-email: Your Name <you@example.com>
License-Expression: MIT
License-File: LICENSE
Requires-Python: <4.0,>=3.9
Requires-Dist: llama-index-core<0.15,>=0.13.0
Requires-Dist: voyageai<0.4.0,>=0.3.6; python_version >= '3.9' and python_version < '3.13'
